hmeter/__init__.py
hmeter/code.py
hmeter-1.0.5.dist-info/LICENSE
hmeter-1.0.5.dist-info/METADATA
hmeter-1.0.5.dist-info/WHEEL
hmeter-1.0.5.dist-info/top_level.txt
hmeter-1.0.5.dist-info/RECORD
