Metadata-Version: 2.1
Name: hmeter
Version: 1.0.5
Summary: A package to check heart related issues.
Home-page: https://github.com/toshihiroryuu/
Author: Athul Mathew Konoor
Author-email: athulmathewkonoor@gmail.com
License: UNKNOWN
Platform: UNKNOWN
Classifier: Programming Language :: Python :: 3
Classifier: License :: OSI Approved :: MIT License
Classifier: Operating System :: OS Independent
Requires-Python: >=3.6
Requires-Dist: gradio (>=1.4.0)
Requires-Dist: scikit-learn (>=0.24.0)
